lighthouse_monitoring/__init__.py
lighthouse_monitoring/main.py
lighthouse_monitoring/schemas.py
lighthouse_monitoring-0.1.3.dist-info/METADATA
lighthouse_monitoring-0.1.3.dist-info/WHEEL
lighthouse_monitoring-0.1.3.dist-info/RECORD
