Metadata-Version: 2.1
Name: lighthouse-monitoring
Version: 0.1.3
Summary: Package to use llm monitoring via LightHouse service
Author: Павел Кочкин
Author-email: pvkochkin@mts.ru
Requires-Python: >=3.11,<4.0
Classifier: Programming Language :: Python :: 3
Classifier: Programming Language :: Python :: 3.11
Requires-Dist: pydantic (>=2.9.1,<3.0.0)
Requires-Dist: requests (>=2.32.3,<3.0.0)
